poseconnect/__init__.py
poseconnect/cli.py
poseconnect/defaults.py
poseconnect/filter.py
poseconnect/identify.py
poseconnect/overlay.py
poseconnect/reconstruct.py
poseconnect/track.py
poseconnect/utils.py
poseconnect/visualize.py
poseconnect-0.17.2.dist-info/LICENSE
poseconnect-0.17.2.dist-info/METADATA
poseconnect-0.17.2.dist-info/WHEEL
poseconnect-0.17.2.dist-info/entry_points.txt
poseconnect-0.17.2.dist-info/top_level.txt
poseconnect-0.17.2.dist-info/RECORD
