Metadata-Version: 2.1
Name: poseconnect
Version: 0.17.2
Summary: Tools for constructing 3D pose tracks from multi-camera 2D poses
Home-page: https://github.com/WildflowerSchools/poseconnect
Author: Theodore Quinn
Author-email: ted.quinn@wildflowerschools.org
License: UNKNOWN
Keywords: pose reconstruction,pose tracking
Platform: UNKNOWN
Classifier: Intended Audience :: Developers
Classifier: License :: OSI Approved :: MIT License
Classifier: Operating System :: OS Independent
Classifier: Programming Language :: Python
License-File: LICENSE
Requires-Dist: wf-smc-kalman (>=0.1.0)
Requires-Dist: wf-cv-utils (>=3.3.0)
Requires-Dist: pandas (>=1.2.2)
Requires-Dist: numpy (>=1.20.1)
Requires-Dist: networkx (>=2.5)
Requires-Dist: matplotlib (>=3.3.4)
Requires-Dist: seaborn (>=0.11.1)
Requires-Dist: tqdm (>=4.57.0)
Requires-Dist: python-slugify (>=4.0.1)
Requires-Dist: python-dateutil (>=2.8)
Requires-Dist: click (>=8.0.0)
